health_calc_pack_py/__init__.py
health_calc_pack_py/app.py
health_calc_pack_py/estrategia.py
health_calc_pack_py/ganho_massa_muscular.py
health_calc_pack_py/imc.py
health_calc_pack_py/macronutrientes.py
health_calc_pack_py/manutencao_peso.py
health_calc_pack_py/perda_gordura.py
health_calc_pack_py/perda_peso_ganho_massa_muscular.py
health_calc_pack_py/static/swagger.json
health_calc_pack_py/test_imc.py
health_calc_pack_py-0.4.1.dist-info/METADATA
health_calc_pack_py-0.4.1.dist-info/WHEEL
health_calc_pack_py-0.4.1.dist-info/RECORD
