Metadata-Version: 2.1
Name: health-calc-pack-py
Version: 0.4.1
Summary: Uma API para calcular IMC e macronutrientes
Author: Angelo Diniz
Author-email: angelo.jose.7l@hotmail.com
Requires-Python: >=3.10,<4.0
Classifier: Programming Language :: Python :: 3
Classifier: Programming Language :: Python :: 3.10
Classifier: Programming Language :: Python :: 3.11
Requires-Dist: flask (>=2.0.2,<3.0.0)
Requires-Dist: flask_swagger_ui (>=3.36.0,<4.0.0)
Requires-Dist: gunicorn (>=20.1.0,<21.0.0)
